micromanubot/__init__.py
micromanubot/__main__.py
micromanubot/build.py
micromanubot/cite.py
micromanubot/cli.py
micromanubot/config.py
micromanubot/figures.py
micromanubot/install.py
micromanubot/new.py
micromanubot/pytinytex.py
micromanubot/template_data/__init__.py
micromanubot/template_data/assets/__init__.py
micromanubot/template_data/assets/arxiv.sty
micromanubot/template_data/assets/orcid.pdf
micromanubot/template_data/build/__init__.py
micromanubot/template_data/build/main.tex
micromanubot/template_data/content/1.introduction.tex
micromanubot/template_data/content/2.results.tex
micromanubot/template_data/content/3.discussion.tex
micromanubot/template_data/content/4.methods.tex
micromanubot/template_data/content/__init__.py
micromanubot/template_data/content/abstract.tex
micromanubot/template_data/content/imports.tex
micromanubot/template_data/content/manual_references.bib
micromanubot/template_data/content/supplement.tex
micromanubot-0.4.3.dist-info/METADATA
micromanubot-0.4.3.dist-info/WHEEL
micromanubot-0.4.3.dist-info/entry_points.txt
micromanubot-0.4.3.dist-info/licenses/LICENSE
micromanubot-0.4.3.dist-info/RECORD
