Metadata-Version: 2.3
Name: micromanubot
Version: 0.4.3
Summary: A build tool for academic manuscripts
Project-URL: Repository, https://github.com/zietzm/micromanubot
Author-email: zietzm <michael.zietz@gmail.com>
License-File: LICENSE
Classifier: Development Status :: 3 - Alpha
Classifier: License :: OSI Approved :: MIT License
Classifier: Programming Language :: Python
Classifier: Programming Language :: Python :: 3 :: Only
Classifier: Programming Language :: Python :: 3.8
Classifier: Programming Language :: Python :: 3.9
Classifier: Programming Language :: Python :: 3.10
Classifier: Programming Language :: Python :: 3.11
Classifier: Programming Language :: Python :: 3.12
Classifier: Topic :: Text Processing :: Markup :: LaTeX
Requires-Python: >=3.8
Requires-Dist: bibtexparser>=2.0.0b7
Requires-Dist: pydantic>=2.7.1
Requires-Dist: pylatexenc>=2.10
Requires-Dist: pyrate-limiter>=3.6.0
Requires-Dist: requests>=2.31.0
Requires-Dist: rich>=13.7.1
Requires-Dist: tomlkit>=0.12.4
Requires-Dist: validators>=0.28.1
